lib99ocl/__init__.py
lib99ocl/version.py
lib99ocl/src/README.md
lib99ocl/src/hyperg_1F1.c
lib99ocl/src/print_devices.c
lib99ocl/src/test.c
lib99ocl/src/test2.c
lib99ocl/src/build/CMakeFiles/3.23.2/CompilerIdC/CMakeCCompilerId.c
lib99ocl/src/exposed/complex.ocl
lib99ocl/src/exposed/core.ocl
lib99ocl/src/exposed/kernels.ocl
lib99ocl/src/exposed/lineshapes.ocl
lib99ocl/src/exposed/special.ocl
lib99ocl/src/kernels/kernels.ocl
lib99ocl/src/kernels/special.ocl
lib99ocl/src/lib99ocl/complex.c
lib99ocl/src/lib99ocl/complex.h
lib99ocl/src/lib99ocl/constants.h
lib99ocl/src/lib99ocl/core.c
lib99ocl/src/lib99ocl/core.h
lib99ocl/src/lib99ocl/cspecial.c
lib99ocl/src/lib99ocl/cspecial.h
lib99ocl/src/lib99ocl/cuda.h
lib99ocl/src/lib99ocl/error.c
lib99ocl/src/lib99ocl/error.h
lib99ocl/src/lib99ocl/hypergeom.c
lib99ocl/src/lib99ocl/hypergeom2.c
lib99ocl/src/lib99ocl/integration.c
lib99ocl/src/lib99ocl/integration.h
lib99ocl/src/lib99ocl/lineshapes.c
lib99ocl/src/lib99ocl/lineshapes.h
lib99ocl/src/lib99ocl/machine.h
lib99ocl/src/lib99ocl/odesolvers.c
lib99ocl/src/lib99ocl/opencl.h
lib99ocl/src/lib99ocl/random.c
lib99ocl/src/lib99ocl/random.h
lib99ocl/src/lib99ocl/special.c
lib99ocl/src/lib99ocl/special.h
lib99ocl/src/lib99ocl/stats.c
lib99ocl/src/lib99ocl/stats.h
lib99ocl/src/lib99ocl/cspecial/bessel.c
lib99ocl/src/lib99ocl/cspecial/bessel.h
lib99ocl/src/lib99ocl/cspecial/cerf.c
lib99ocl/src/lib99ocl/cspecial/cerf.h
lib99ocl/src/lib99ocl/cspecial/gamma.c
lib99ocl/src/lib99ocl/cspecial/gamma.h
lib99ocl/src/lib99ocl/cspecial/spherical_harmonics.c
lib99ocl/src/lib99ocl/cspecial/spherical_harmonics.h
lib99ocl/src/lib99ocl/details/bessel.c
lib99ocl/src/lib99ocl/details/cerf.c
lib99ocl/src/lib99ocl/details/cigamma.c
lib99ocl/src/lib99ocl/details/complex.c
lib99ocl/src/lib99ocl/details/gamma.c
lib99ocl/src/lib99ocl/gsl/build.h
lib99ocl/src/lib99ocl/gsl/gsl-histogram.c
lib99ocl/src/lib99ocl/gsl/gsl-randist.c
lib99ocl/src/lib99ocl/gsl/gsl_inline.h
lib99ocl/src/lib99ocl/gsl/gsl_machine.h
lib99ocl-0.0.0.dev13.dist-info/LICENSE
lib99ocl-0.0.0.dev13.dist-info/METADATA
lib99ocl-0.0.0.dev13.dist-info/WHEEL
lib99ocl-0.0.0.dev13.dist-info/top_level.txt
lib99ocl-0.0.0.dev13.dist-info/RECORD
