Metadata-Version: 2.1
Name: lib99ocl
Version: 0.0.0.dev13
Summary: OpenCL C99 library
Home-page: https://github.com/marromlam/py-lib99ocl.git
Download-URL: https://github.com/marromlam/py-lib99ocl.git
Author: Marcos Romero Lamas
Author-email: marromlam@gmail.com
License: MIT License Copyright (c) 2021 Marcos Romero Lamas
Keywords: computational physics
Platform: Linux
Platform: macOS
Platform: Windows
Requires-Python: >=3.5
License-File: LICENSE
